comrak/__init__.py
comrak/__init__.pyi
comrak/comrak.cpython-312-arm-linux-gnueabihf.so
comrak/py.typed
comrak_ext-0.1.6.dist-info/METADATA
comrak_ext-0.1.6.dist-info/WHEEL
comrak_ext-0.1.6.dist-info/licenses/LICENSE
comrak_ext-0.1.6.dist-info/RECORD
