Metadata-Version: 2.4
Name: comrak-ext
Version: 0.1.6
Classifier: Intended Audience :: Developers
Classifier: License :: OSI Approved :: MIT License
Classifier: Programming Language :: Rust
Classifier: Programming Language :: Python :: Implementation :: CPython
Classifier: Programming Language :: Python :: Implementation :: PyPy
Classifier: Operating System :: OS Independent
Classifier: Programming Language :: Python :: 3
Classifier: Programming Language :: Python :: 3.10
Classifier: Programming Language :: Python :: 3.11
Classifier: Programming Language :: Python :: 3.12
Classifier: Programming Language :: Python :: 3.13
Classifier: Programming Language :: Python :: 3.9
Requires-Dist: markdown>=3.7 ; extra == 'bench'
Requires-Dist: markdown2>=2.5.3 ; extra == 'bench'
Requires-Dist: maturin[patchelf]>=1.8.2 ; extra == 'dev'
Requires-Dist: pdm>=2.22.3 ; extra == 'dev'
Requires-Dist: pdm-bump>=0.9.10 ; extra == 'dev'
Requires-Dist: pre-commit>=4.1.0 ; extra == 'dev'
Provides-Extra: bench
Provides-Extra: dev
License-File: LICENSE
Summary: Extended Python bindings for the Comrak Rust library, a fast CommonMark/GFM parser
Keywords: markdown,html,rust,commonmark,gfm,parser
Author-email: Martin Chrástek <chrastek12@gmail.com>
Requires-Python: >=3.9
Project-URL: Homepage, https://github.com/Martin005/comrak-ext
Project-URL: Repository, https://github.com/Martin005/comrak-ext.git
